manim3/__init__.py
manim3/animatables/camera.py
manim3/animatables/graph.py
manim3/animatables/lighting.py
manim3/animatables/mesh.py
manim3/animatables/model.py
manim3/animatables/point.py
manim3/animatables/shape.py
manim3/animatables/animatable/action.py
manim3/animatables/animatable/animatable.py
manim3/animatables/animatable/animation.py
manim3/animatables/animatable/piecewiser.py
manim3/animatables/arrays/animatable_array.py
manim3/animatables/arrays/animatable_color.py
manim3/animatables/arrays/animatable_float.py
manim3/animatables/arrays/model_matrix.py
manim3/animatables/lights/ambient_light.py
manim3/animatables/lights/point_light.py
manim3/constants/constants.py
manim3/constants/custom_typing.py
manim3/constants/palette.py
manim3/constants/pyglet_constants.py
manim3/constants/rates.py
manim3/lazy/lazy.py
manim3/lazy/lazy_descriptor.py
manim3/lazy/lazy_object.py
manim3/lazy/lazy_slot.py
manim3/mobjects/cached_mobject.py
manim3/mobjects/image_mobject.py
manim3/mobjects/mobject.py
manim3/mobjects/svg_mobject.py
manim3/mobjects/graph_mobjects/graph_mobject.py
manim3/mobjects/graph_mobjects/line.py
manim3/mobjects/graph_mobjects/polyline.py
manim3/mobjects/mesh_mobjects/mesh_mobject.py
manim3/mobjects/mesh_mobjects/parametric_surface.py
manim3/mobjects/mesh_mobjects/plane.py
manim3/mobjects/mesh_mobjects/sphere.py
manim3/mobjects/shape_mobjects/circle.py
manim3/mobjects/shape_mobjects/polygon.py
manim3/mobjects/shape_mobjects/polyhedra.py
manim3/mobjects/shape_mobjects/regular_polygon.py
manim3/mobjects/shape_mobjects/shape_mobject.py
manim3/mobjects/shape_mobjects/square.py
manim3/mobjects/string_mobjects/code_mobject.py
manim3/mobjects/string_mobjects/math_mobject.py
manim3/mobjects/string_mobjects/text_mobject.py
manim3/mobjects/string_mobjects/typst_mobject.py
manim3/rendering/field.py
manim3/rendering/mgl_enums.py
manim3/rendering/vertex_array.py
manim3/rendering/buffers/attributes_buffer.py
manim3/rendering/buffers/buffer.py
manim3-0.1.0.dist-info/LICENSE.md
manim3-0.1.0.dist-info/WHEEL
manim3-0.1.0.dist-info/METADATA
manim3-0.1.0.dist-info/RECORD
