Metadata-Version: 2.1
Name: manim3
Version: 0.1.0
Summary: A personal variant of manim
Author: YishiMichael
Requires-Python: >=3.12
Classifier: Programming Language :: Python
Requires-Dist: attrs
Requires-Dist: colour
Requires-Dist: ffmpeg-python
Requires-Dist: lru-dict
Requires-Dist: mapbox-earcut
Requires-Dist: moderngl
Requires-Dist: numpy
Requires-Dist: pillow
Requires-Dist: pyclipr
Requires-Dist: pyglet
Requires-Dist: rich
Requires-Dist: svgelements
